aks.py
aks-0.1.0.dist-info/LICENSE
aks-0.1.0.dist-info/METADATA
aks-0.1.0.dist-info/WHEEL
aks-0.1.0.dist-info/top_level.txt
aks-0.1.0.dist-info/RECORD
